fixerio/__init__.py
fixerio/client.py
fixerio/exceptions.py
fixerio-0.1.1.dist-info/DESCRIPTION.rst
fixerio-0.1.1.dist-info/METADATA
fixerio-0.1.1.dist-info/RECORD
fixerio-0.1.1.dist-info/WHEEL
fixerio-0.1.1.dist-info/metadata.json
fixerio-0.1.1.dist-info/top_level.txt
