Metadata-Version: 1.1
Name: fixerio
Version: 0.1.1
Summary: A Python client for Fixer.io
Home-page: https://github.com/amatellanes/fixerio
Author: Adrian Matellanes
Author-email: matellanesadrian@gmail.com
License: MIT License
Platform: UNKNOWN
Classifier: Development Status :: 4 - Beta
Classifier: Intended Audience :: Developers
Classifier: Natural Language :: English
Classifier: License :: OSI Approved :: MIT License
Classifier: Programming Language :: Python
Classifier: Programming Language :: Python :: 2.7
Classifier: Programming Language :: Python :: 3
Classifier: Programming Language :: Python :: 3.3
Classifier: Programming Language :: Python :: 3.4
Classifier: Programming Language :: Python :: 3.5
Classifier: Programming Language :: Python :: Implementation :: PyPy
